wdsparql/__init__.py
wdsparql/_version.py
wdsparql/exceptions.py
wdsparql/wdsparqlmagic.py
wdsparql-0.0.3.dist-info/LICENSE
wdsparql-0.0.3.dist-info/METADATA
wdsparql-0.0.3.dist-info/WHEEL
wdsparql-0.0.3.dist-info/top_level.txt
wdsparql-0.0.3.dist-info/RECORD
