Metadata-Version: 2.1
Name: wdsparql
Version: 0.0.3
Summary: Run Wikidata Sparql queries directly on your notebook
Home-page: https://github.com/daviddavo/wdsparqlmagic
Author: David Davó
Author-email: david@ddavo.me
License: UNKNOWN
Project-URL: Bug Tracker, https://github.com/daviddavo/wdsparqlmagic/issues
Platform: UNKNOWN
Classifier: Programming Language :: Python :: 3
Classifier: License :: OSI Approved :: MIT License
Classifier: Development Status :: 4 - Beta
Classifier: Framework :: IPython
Requires-Python: >=3.6
License-File: LICENSE
Requires-Dist: requests (>=2.20)
Requires-Dist: ipython (>=7.0.0)
Requires-Dist: pandas (>=1.1)
